acord/__init__.py
acord/client.py
acord/errors.py
acord/core/decoders.py
acord/core/heartbeat.py
acord/core/helpers.py
acord/core/http.py
acord/core/signals/gateway.py
acord/core/signals/voice.py
acord/models/__init__.py
acord/models/user.py
ACord-0.0.1a0.dist-info/LICENSE
ACord-0.0.1a0.dist-info/METADATA
ACord-0.0.1a0.dist-info/WHEEL
ACord-0.0.1a0.dist-info/top_level.txt
ACord-0.0.1a0.dist-info/RECORD
